principal_portfolios/__init__.py
principal_portfolios/principal_portfolios.py
principal_portfolios/utils.py
principal_portfolios-1.0.5.dist-info/METADATA
principal_portfolios-1.0.5.dist-info/WHEEL
principal_portfolios-1.0.5.dist-info/top_level.txt
principal_portfolios-1.0.5.dist-info/RECORD
