Metadata-Version: 2.4
Name: principal_portfolios
Version: 1.0.5
Summary: A Python implementation of the Principal Portfolios methodology by Kelly, Malamud, and Pedersen (2023), enabling optimal asset allocation by exploiting cross-predictability among asset returns.
Home-page: https://github.com/aminizadyar/Principal-Portfolios
Author: Amin Izadyar
Author-email: a.izadyar23@imperial.ac.uk
Classifier: Programming Language :: Python :: 3
Classifier: License :: OSI Approved :: MIT License
Classifier: Operating System :: OS Independent
Requires-Python: >=3.6
Dynamic: author
Dynamic: author-email
Dynamic: classifier
Dynamic: description
Dynamic: description-content-type
Dynamic: home-page
Dynamic: requires-python
Dynamic: summary
